dipsl/DIP_Environment.py
dipsl/DIP_Main.py
dipsl/DIP_Source.py
dipsl/DIP_Unit.py
dipsl/DIP_UnitList.py
dipsl/__init__.py
dipsl/datatypes/DIP_Type.py
dipsl/datatypes/DIP_Type_Boolean.py
dipsl/datatypes/DIP_Type_Float.py
dipsl/datatypes/DIP_Type_Integer.py
dipsl/datatypes/DIP_Type_Number.py
dipsl/datatypes/DIP_Type_String.py
dipsl/datatypes/__init__.py
dipsl/docs/DIP_Sphinx_Docs.py
dipsl/docs/__init__.py
dipsl/nodes/DIP_Node.py
dipsl/nodes/DIP_NodeBase.py
dipsl/nodes/DIP_NodeSelect.py
dipsl/nodes/DIP_Node_Boolean.py
dipsl/nodes/DIP_Node_Case.py
dipsl/nodes/DIP_Node_Condition.py
dipsl/nodes/DIP_Node_Constant.py
dipsl/nodes/DIP_Node_Empty.py
dipsl/nodes/DIP_Node_Float.py
dipsl/nodes/DIP_Node_Format.py
dipsl/nodes/DIP_Node_Group.py
dipsl/nodes/DIP_Node_Import.py
dipsl/nodes/DIP_Node_Integer.py
dipsl/nodes/DIP_Node_Mod.py
dipsl/nodes/DIP_Node_Option.py
dipsl/nodes/DIP_Node_Source.py
dipsl/nodes/DIP_Node_String.py
dipsl/nodes/DIP_Node_Table.py
dipsl/nodes/DIP_Node_Unit.py
dipsl/nodes/DIP_Parser.py
dipsl/nodes/__init__.py
dipsl/pygments/DIP_Lexer_Schema.py
dipsl/pygments/DIP_Lexer_Style.py
dipsl/pygments/DIP_Lexer_Syntax.py
dipsl/pygments/__init__.py
dipsl/settings/__init__.py
dipsl/solvers/DIP_Solver_Function.py
dipsl/solvers/DIP_Solver_Logical.py
dipsl/solvers/DIP_Solver_Numerical.py
dipsl/solvers/DIP_Solver_Templates.py
dipsl/solvers/DIP_Solver_Units.py
dipsl/solvers/__init__.py
dipsl-0.2.2.dist-info/METADATA
dipsl-0.2.2.dist-info/WHEEL
dipsl-0.2.2.dist-info/licenses/LICENSE
dipsl-0.2.2.dist-info/RECORD
