Metadata-Version: 2.1
Name: dipsl
Version: 0.2.2
Summary: Python implementation of Dimensional Input Parameter Serialization Language (DIPSL)
Project-URL: Homepage, https://github.com/dipsl/pydipsl
Project-URL: Bug Tracker, https://github.com/dipsl/pydipsl/issues
Author-email: Ondrej Pego Jaura <dipsl.vrtulka23@gmail.com>
License-File: LICENSE
Classifier: License :: OSI Approved :: MIT License
Classifier: Operating System :: OS Independent
Classifier: Programming Language :: Python :: 3
Requires-Python: >=3.7
